pulumi_miniflux/__init__.py
pulumi_miniflux/_utilities.py
pulumi_miniflux/miniflux_service.py
pulumi_miniflux/provider.py
pulumi_miniflux/py.typed
pulumi_miniflux-0.0.16.dist-info/METADATA
pulumi_miniflux-0.0.16.dist-info/WHEEL
pulumi_miniflux-0.0.16.dist-info/top_level.txt
pulumi_miniflux-0.0.16.dist-info/RECORD
