Metadata-Version: 2.1
Name: pulumi-miniflux
Version: 0.0.16
Summary: UNKNOWN
Home-page: UNKNOWN
License: UNKNOWN
Platform: UNKNOWN
Requires-Dist: parver (>=0.2.1)
Requires-Dist: pulumi (<4.0.0,>=3.0.0)
Requires-Dist: pulumi-aws (<5.0.0,>=4.0.0)
Requires-Dist: semver (>=2.8.1)
